{
    "sim": {
        "ikresult_success": 1,
        "joint_revolute_subtype": 10,
        "mujoco_body_friction1": 43001,
        "vortex_joint_frictionproportionalbc": 22004,
        "jointfloatparam_upper_limit": 2017,
        "jointmode_dependent": 4,
        "buffer_float": 6,
        "stringparam_scenedefaultdir": 132,
        "ode_global_stepsize": 9001,
        "displayattribute_selected": 8,
        "boolparam_hierarchy_toolbarbutton_enabled": 35,
        "newton_global_exactsolver": 29002,
        "objectspecialproperty_detectable_inductive": 128,
        "mujoco_joint_damping": 40017,
        "mujoco_global_boundmass": 37008,
        "dlgstyle_message": 0,
        "mujoco_dummy_range1": 46001,
        "visionfloatparam_pov_aperture": 1015,
        "boolparam_statustext_open": 18,
        "vortex_body_autoangulardampingtensionratio": 24033,
        "plugininfo_extversionstr": 0,
        "ik_pseudo_inverse_method": 0,
        "dummy_linktype_gcs_target": 4,
        "intparam_videoencoderindex": 43,
        "ode_global_internalscalingfactor": 9002,
        "jointfloatparam_intrinsic_y": 2006,
        "particle_points1": 0,
        "verbosity_errors": 200,
        "filtercomponent_scaleandoffsetcolors": 27,
        "bullet_constraintsolvertype_sequentialimpulse": 0,
        "drawing_itemtransparency": 524288,
        "dummy_linktype_gcs_loop_closure": 2,
        "displayattribute_trianglewireframe": 16384,
        "ruckig_nosync": 3,
        "camerafloatparam_pov_blur_distance": 9005,
        "objfloatparam_modelbbox_max_x": 24,
        "jointintparam_dynctrlmode": 2039,
        "dummyintparam_follow_path": 10001,
        "drawing_linestrip": 8,
        "arrayparam_background_color2": 4,
        "intparam_mouse_x": 22,
        "mujoco_dummy_limited": 48001,
        "vortex_joint_lowerlimitdamping": 21001,
        "object_no_subtype": 200,
        "moduleinfo_verbosity": 3,
        "intparam_simulation_warning_disabled_mask": 33,
        "distcalcmethod_dac_if_nonzero": 6,
        "vortex_body_normalmangulararaxisfrictionmodel": 25005,
        "filtercomponent_intensityscale": 25,
        "sim_lang_undefined": -1,
        "intparam_platform": 19,
        "intparam_compilation_version": 4,
        "filtercomponent_swapwithbuffer1": 29,
        "drawing_auxchannelcolor1": 2097152,
        "buffer_uint8rgb": 8,
        "stringparam_app_arg8": 9,
        "displayattribute_noghosts": 8388608,
        "dlgret_still_open": 0,
        "vortex_joint_motorconstraintfrictionloss": 21011,
        "vortex_body_seclinearaxisfriction": 24002,
        "jointintparam_motor_enabled": 2000,
        "vortex_body_primlinearaxisslide": 24018,
        "childscriptcall_initialization": 2,
        "jointdynctrl_free": 0,
        "customizationscriptcall_lastbeforeinstanceswitch": 11,
        "vortex_joint_a2stiffness": 21043,
        "vortex_joint_a2damping": 21044,
        "newton_global_highjointaccuracy": 29003,
        "customizationscriptcall_nonsimulation": 3,
        "particle_itemcolors": 4096,
        "vortex_joint_frictionenabledbc": 22003,
        "drawing_itemsizes": 128,
        "mainscriptcall_initialization": 2,
        "customizationscriptcall_simulationactuation": 6,
        "ode_joint_bounce": 12003,
        "stringparam_machine_id_legacy": 120,
        "mujoco_global_overridekin": 38008,
        "displayattribute_forbidedges": 256,
        "buffer_uint16": 2,
        "boolparam_video_recording_triggered": 29,
        "boolparam_show_w_receivers": 54,
        "bullet_body_autoshrinkconvex": 8004,
        "objintparam_illumination_handle": 32,
        "mujoco_global_wind3": 37005,
        "vortex_bodyfrictionmodel_prophigh": 3,
        "intparam_dynamic_iteration_count": 37,
        "floatparam_simulation_time_step": 1,
        "dynmat_reststackgrasp": 2310017,
        "particle_ignoresgravity": 256,
        "vortex_bodyfrictionmodel_neutral": 5,
        "jointmode_dynamic": 5,
        "appobj_collection_type": 115,
        "filtercomponent_binary": 28,
        "stringparam_video_filename": 1,
        "stringparam_application_path": 0,
        "scriptthreadresume_sensing_first": 3,
        "displayattribute_nodrawingobjects": 33554432,
        "vortex_body_normalangularaxisslip": 24027,
        "primitiveshape_plane": 1,
        "primitiveshape_heightfield": 7,
        "newton_joint_dependencyoffset": 30002,
        "scriptthreadresume_actuation_last": 2,
        "jointfloatparam_intrinsic_x": 2005,
        "drawing_50percenttransparency": 8192,
        "dlgstyle_input": 1,
        "jointintparam_dynposctrltype": 2041,
        "mujoco_global_impratio": 37002,
        "jointfloatparam_maxjerk": 2038,
        "stringparam_legacymachinetag": 142,
        "boolparam_rosinterface_donotrunmainscript": 48,
        "verbosity_loadinfos": 400,
        "particle_emissioncolor": 16384,
        "scriptattribute_enabled": 4,
        "modelproperty_not_respondable": 64,
        "object_joint_type": 1,
        "vortex_body_normalangularaxisfrictionmodel": 25005,
        "jointfloatparam_vortex_dep_multiplication": 2032,
        "dynmat_default": 2310013,
        "handle_main_script": -5,
        "jointfloatparam_intrinsic_qy": 2009,
        "mujoco_global_integrator": 38003,
        "stringparam_scene_unique_id": 118,
        "msgbox_return_no": 1,
        "vortex_body_normalangularaxisfriction": 24005,
        "filtercomponent_velodyne": 37,
        "scriptintparam_lang": 6,
        "bullet_body_nondefaultcollisionmargingfactor": 6006,
        "mujoco_joint_solimpfriction3": 40013,
        "mujoco_global_kinmass": 37018,
        "boolparam_ik_handling_enabled": 4,
        "syscb_afterinstanceswitch": 12,
        "proximitysensor_cone_subtype": 33,
        "banner_fullyfacingcamera": 256,
        "ode_joint_pospid3": 12008,
        "childscriptattribute_enabled": 4,
        "mujoco_global_kininertia": 37019,
        "navigation_ctrlselection": 1024,
        "message_object_selection_changed": 2,
        "colorcomponent_auxiliary": 5,
        "banner_followparentvisibility": 16,
        "modelproperty_not_model": 61440,
        "shapefloatparam_edge_angle": 3026,
        "primitiveshape_capsule": 8,
        "colorcomponent_specular": 2,
        "vortex_joint_p1frictionloss": 21023,
        "syscb_suspended": 8,
        "stringparam_app_arg2": 3,
        "newton_global_constraintsolvingiterations": 28001,
        "mujoco_global_rebuildtrigger": 38010,
        "addonscriptcall_cleanup": 1,
        "filtercomponent_frombuffer1": 7,
        "shapefloatparam_init_ang_velocity_z": 3022,
        "navigation_camerafly": 6,
        "verbosity_tracelua": 800,
        "boolparam_mill_handling_enabled": 11,
        "vortex_joint_p0damping": 21014,
        "syscb_nonsimulation": 3,
        "vortex_body_seclinearaxisslip": 24024,
        "intparam_stop_request_counter": 29,
        "mujoco_joint_solimplimit2": 40004,
        "boolparam_objectrotate_toolbarbutton_enabled": 38,
        "msgbox_type_question": 1,
        "cameraintparam_disabled_light_components": 9000,
        "buffer_double": 7,
        "filtercomponent_imagetocoord": 35,
        "vortex_joint_motorfrictionenabled": 23001,
        "syscb_selchange": 44,
        "displayattribute_colorcoded": 8192,
        "displayattribute_ignorelayer": 1024,
        "ikresult_not_performed": 0,
        "pathproperty_keep_x_up": 2048,
        "cameraintparam_perspective_operation": 9010,
        "vortex_joint_dependencyoffset": 21049,
        "drawing_backfaceculling": 256,
        "shapestringparam_color_name": 3023,
        "mujoco_joint_solreffriction1": 40009,
        "buffer_uint8rgba": 10,
        "drawing_auxchannelcolor2": 4194304,
        "vortex_body_autosleeplinearspeedthreshold": 24028,
        "objectspecialproperty_collidable": 1,
        "message_scene_loaded": 8,
        "object_graph_type": 2,
        "vortex_joint_pospid3": 21054,
        "drawing_painttag": 1024,
        "vortex_joint_pospid1": 21052,
        "vortex_joint_p2frictioncoeff": 21027,
        "boolparam_vision_sensor_handling_enabled": 10,
        "arrayparam_rayorigin": 7,
        "appobj_texture_type": 120,
        "objectproperty_selectmodelbaseinstead": 128,
        "mirrorfloatparam_height": 12001,
        "particle_points2": 1,
        "syscb_vision": 30,
        "verbosity_msgs": 450,
        "handle_default": -9,
        "floatparam_mintrisizerel": 7,
        "mujoco_body_margin": 43012,
        "intparam_flymode_camera_handle": 6,
        "handle_app": -13,
        "mujoco_joint_solimplimit1": 40003,
        "verbosity_debug": 600,
        "verbosity_traceall": 900,
        "jointdynctrl_force": 1,
        "mujoco_global_boundinertia": 37009,
        "simulation_advancing_abouttostop": 21,
        "camerafloatparam_perspective_angle": 9001,
        "objectproperty_cannotdelete": 8192,
        "buttonproperty_isdown": 256,
        "vortex_body_primangulararaxisfrictionmodel": 25003,
        "distcalcmethod_sqrt_dl2_and_dac2": 4,
        "vortex_body_secangularaxisfrictionmodel": 25004,
        "vortex_joint_a1frictionloss": 21041,
        "shapeintparam_culling": 3014,
        "message_pick_select_down": 11,
        "boolparam_mirrors_enabled": 22,
        "filtercomponent_originalimage": 1,
        "ode_global_bitcoded": 10002,
        "appobj_simulation_type": 112,
        "navigation_cameraangle": 5,
        "boolparam_display_enabled": 16,
        "filtercomponent_addbuffer1": 10,
        "verbosity_warnings": 300,
        "pathproperty_closed_path": 4,
        "vortex_joint_a2frictionloss": 21047,
        "drawing_cyclic": 4096,
        "mujoco_global_overridecontacts": 39005,
        "scriptthreadresume_default": 0,
        "objfloatparam_transparency_offset": 28,
        "appobj_ik_type": 113,
        "mujoco_body_solmix": 43011,
        "drawing_lines": 1,
        "forcefloatparam_error_a": 5003,
        "pure_primitive_cuboid": 3,
        "jointfloatparam_pid_p": 2002,
        "displayattribute_colorcodedpickpass": 4096,
        "floatparam_physicstimestep": 5,
        "stream_transf_derivative": 1,
        "cameraintparam_trackedobject": 9011,
        "visionfarrayparam_viewfrustum": 1019,
        "vortex_body_normalangularaxisslide": 24022,
        "jointfloatparam_error_x": 2022,
        "drawing_discpoints": 5,
        "objfloatparam_abs_y_velocity": 12,
        "boolparam_stop_toolbarbutton_enabled": 44,
        "objfloatparam_objbbox_min_x": 15,
        "vortex_body_primangularaxisslide": 24020,
        "vortex_body_primangularaxisslip": 24025,
        "vortex_body_adhesiveforce": 24015,
        "boolparam_browser_toolbarbutton_enabled": 36,
        "mujoco_joint_polycoef1": 40023,
        "mujoco_global_overridesolimp5": 37017,
        "ik_z_constraint": 4,
        "boolparam_shape_textures_are_visible": 15,
        "bullet_global_constraintsolvingiterations": 1001,
        "stream_transf_raw": 0,
        "scriptintparam_enabled": 4,
        "rml_phase_sync_if_possible": 0,
        "vortex_bodyfrictionmodel_proplow": 2,
        "objectproperty_selectinvisible": 2048,
        "scriptintparam_objecthandle": 5,
        "objectproperty_cannotdeleteduringsim": 16384,
        "modelproperty_not_measurable": 2,
        "shapeintparam_edge_visibility": 3024,
        "vortex_joint_a1frictionmaxforce": 21040,
        "particle_respondable5to8": 64,
        "arrayparam_ambient_light": 5,
        "addonscriptcall_suspend": 16,
        "filtercomponent_edge": 21,
        "stringparam_uniqueid": 126,
        "boolparam_waiting_for_trigger": 45,
        "displayattribute_originalcolors": 512,
        "pure_primitive_spheroid": 4,
        "filtercomponent_subtractbuffer1": 11,
        "customizationscriptcall_cleanup": 1,
        "jointfloatparam_kc_k": 2018,
        "api_error_output": 2,
        "forcefloatparam_error_pos": 5006,
        "visionintparam_perspective_operation": 1018,
        "addonscriptcall_initialization": 2,
        "plugininfo_builddatestr": 1,
        "plugininfo_extversionint": 2,
        "mujoco_body_priority": 44002,
        "bullet_constraintsolvertype_projectedgaussseidel": 3,
        "boolparam_rayvalid": 56,
        "mujoco_joint_solimplimit4": 40006,
        "scriptstringparam_nameext": 3,
        "objectspecialproperty_detectable_all": 496,
        "msgbox_type_critical": 3,
        "shapeintparam_convex_check": 3018,
        "banner_nobackground": 4,
        "ik_gamma_constraint": 16,
        "vortex_body_primangularaxisfriction": 24003,
        "shapefloatparam_texture_y": 3007,
        "jointmode_kinematic": 0,
        "mujoco_body_solimp2": 43007,
        "visionfloatparam_perspective_angle": 1004,
        "shapefloatparam_init_ang_velocity_y": 3021,
        "bullet_joint_pospid1": 3006,
        "stringparam_addonpath": 131,
        "newton_joint_pospid2": 30004,
        "api_error_report": 1,
        "syscb_joint": 42,
        "mujoco_body_solimp1": 43006,
        "mujoco_global_density": 37006,
        "objfloatparam_objbbox_max_z": 20,
        "filtercomponent_verticalflip": 14,
        "volume_cone": 3,
        "dummylink_dyntendon": 7,
        "vortex_body_primlinearaxisslip": 24023,
        "vortex_joint_relaxationenabledbc": 22002,
        "displayattribute_noparticles": 67108864,
        "dummy_linktype_gcs_tip": 3,
        "intparam_scene_index": 34,
        "boolparam_gcs_handling_enabled": 5,
        "vortex_joint_a1frictioncoeff": 21039,
        "sim_lang_python": 1,
        "boolparam_headless": 34,
        "particle_painttag": 65536,
        "primitiveshape_disc": 2,
        "forcefloatparam_error_g": 5005,
        "visionfloatparam_ortho_size": 1005,
        "newton_body_kineticfriction": 33002,
        "drawing_vertexcolors": 64,
        "rml_recompute_trajectory": 0,
        "vortex_joint_lowerlimitmaxforce": 21007,
        "distcalcmethod_dac": 1,
        "vortex_body_skinthickness": 24032,
        "navigation_camerazoom": 3,
        "vortex_joint_p2stiffness": 21025,
        "ode_joint_stopcfm": 12002,
        "objfloatparam_modelbbox_max_z": 26,
        "drawing_emissioncolor": 65536,
        "stringparam_additionalpythonpath": 135,
        "jointfloatparam_intrinsic_qz": 2010,
        "shapeintparam_wireframe": 3015,
        "filedlg_type_save": 1,
        "ode_global_randomseed": 10003,
        "vortex_bodyfrictionmodel_scaledbox": 1,
        "ode_global_erp": 9004,
        "objectproperty_canupdatedna": 1024,
        "proximitysensor_cylinder_subtype": 31,
        "primitiveshape_cone": 6,
        "pathproperty_automatic_orientation": 8,
        "moduleinfo_statusbarverbosity": 4,
        "mujoco_global_njmax": 38005,
        "drawing_cubepts": 12,
        "vortex_body_bitcoded": 25006,
        "shapefloatparam_texture_b": 3010,
        "banner_right": 2,
        "customizationscriptcall_simulationpause": 8,
        "handle_all_except_self": -10,
        "dynmat_highfriction": 2310014,
        "handleflag_depthbuffermeters": 8388608,
        "mujoco_body_friction3": 43003,
        "newton_joint_dependencyfactor": 30001,
        "volume_disc": 2,
        "volume_pyramid": 0,
        "plugininfo_statusbarverbosity": 4,
        "jointfloatparam_spherical_qy": 2014,
        "floatparam_dynamic_step_size": 3,
        "jointmode_ik": 2,
        "dlgstyle_ok": 2,
        "buttonproperty_nobackgroundcolor": 1024,
        "objectspecialproperty_renderable": 512,
        "mujoco_global_iterations": 38002,
        "proximitysensor_pyramid_subtype": 30,
        "mujoco_dummy_margin": 46010,
        "intparam_visible_layers": 11,
        "buffer_clamp": 256,
        "vortex_body_primaxisvectorx": 24034,
        "jointfloatparam_error_a": 2025,
        "scriptstringparam_name": 1,
        "vortex_joint_a0frictioncoeff": 21033,
        "jointdynctrl_position": 8,
        "dlgstyle_ok_cancel": 3,
        "handleflag_resetforcetorque": 12582912,
        "vortex_body_autosleepangularspeedthreshold": 24030,
        "vortex_global_contacttolerance": 18003,
        "scriptthreadresume_custom": 5,
        "stringparam_dlgverbosity": 123,
        "bullet_joint_stoperp": 3001,
        "proximitysensor_disc_subtype": 32,
        "boolparam_force_calcstruct_all_visible": 39,
        "joint_spherical_subtype": 12,
        "scripttype_sandboxscript": 8,
        "handleflag_abscoords": 8388608,
        "intparam_scene_unique_id": 20,
        "handleflag_model": 8388608,
        "objfloatparam_abs_z_velocity": 13,
        "intparam_current_page": 5,
        "object_camera_type": 3,
        "arrayparam_raydirection": 8,
        "modelproperty_not_collidable": 1,
        "dlgret_no": 4,
        "drawing_wireframe": 512,
        "colorcomponent_diffuse": 1,
        "drawing_discpts": 11,
        "ode_joint_pospid2": 12007,
        "intparam_dynamic_step_divider": 7,
        "visionintparam_pov_blur_sampled": 1016,
        "ode_joint_stoperp": 12001,
        "ode_body_angulardamping": 15005,
        "mujoco_joint_polycoef3": 40025,
        "handle_all_except_explicit": -3,
        "vortex_body_normalangularaxisstaticfrictionscale": 24010,
        "mill_cylinder_subtype": 41,
        "ikresult_fail": 2,
        "intparam_dlgverbosity": 42,
        "vortex_joint_p1stiffness": 21019,
        "vortex_global_internalscalingfactor": 18002,
        "mirrorfloatparam_width": 12000,
        "boolparam_dynamics_handling_enabled": 6,
        "jointfloatparam_intrinsic_z": 2007,
        "dlgstyle_yes_no": 4,
        "floatparam_maxtrisizeabs": 6,
        "shapefloatparam_init_velocity_g": 3022,
        "shapeintparam_sleepmodestart": 3029,
        "handleflag_resettorque": 8388608,
        "handleflag_setmultiple": 4194304,
        "physics_physx": 5,
        "simulation_advancing_running": 17,
        "object_shape_type": 0,
        "mujoco_dummy_range2": 46002,
        "stringparam_remoteapi_temp_file_dir": 16,
        "mujoco_joint_pospid1": 40028,
        "pure_primitive_disc": 2,
        "drawing_points": 0,
        "vortex_body_angularvelocitydamping": 24017,
        "verbosity_none": 100,
        "vortex_joint_a2loss": 21042,
        "shapefloatparam_init_velocity_x": 3000,
        "banner_overlay": 8,
        "visionintparam_entity_to_render": 1008,
        "stringparam_usersettingsdir": 139,
        "handle_single": -8,
        "simulation_advancing_firstafterpause": 20,
        "light_directional_subtype": 3,
        "newton_global_contactmergetolerance": 27002,
        "syscb_aos_suspend": 16,
        "visionintparam_resolution_x": 1002,
        "filtercomponent_addtobuffer1": 30,
        "handleflag_addmultiple": 16777216,
        "buttonproperty_button": 0,
        "arrayparam_random_euler": 6,
        "navigation_camerarotatemiddlebutton": 8192,
        "boolparam_rml2_available": 20,
        "intparam_server_port_start": 9,
        "stringparam_luadir": 136,
        "syscb_customcallback1": 20,
        "handle_tree": -6,
        "vortex_global_bitcoded": 19001,
        "mujoco_global_bitcoded": 38001,
        "mujoco_joint_solimpfriction5": 40015,
        "callbackid_userdefined": 1000,
        "modelproperty_not_visible": 256,
        "colorcomponent_transparency": 4,
        "objectproperty_collapsed": 16,
        "vortex_joint_p0frictioncoeff": 21015,
        "banner_clickselectsparent": 32,
        "stringparam_modeldefaultdir": 133,
        "appobj_distance_type": 111,
        "filtercomponent_frombuffer2": 8,
        "verbosity_scriptinfos": 450,
        "particle_respondable1to4": 32,
        "shapeintparam_compound": 3016,
        "shapestringparam_colorname": 3032,
        "modelproperty_not_showasinsidemodel": 1024,
        "scripttype_childscript": 1,
        "stringparam_defaultpython": 134,
        "shapefloatparam_texture_z": 3008,
        "mainscriptcall_cleanup": 1,
        "ode_global_computeinertias": 11003,
        "mujoco_global_multiccd": 39003,
        "mujoco_global_wind1": 37003,
        "shapefloatparam_init_velocity_a": 3020,
        "objintparam_unique_id": 37,
        "jointfloatparam_screw_pitch": 2034,
        "boolparam_full_model_copy_from_api": 24,
        "vortex_body_seclinaxissameasprimlinaxis": 26006,
        "boolparam_force_show_wireless_reception": 28,
        "vortex_joint_lowerlimitrestitution": 21005,
        "objfloatparam_abs_rot_velocity": 14,
        "buffer_uint32": 4,
        "shapefloatparam_texture_a": 3009,
        "shapeintparam_convex": 3017,
        "boolparam_execunsafeext": 59,
        "modelproperty_scripts_inactive": 512,
        "mujoco_dummy_solimplimit1": 46005,
        "handle_self": -4,
        "scriptdebug_syscalls": 1,
        "vortex_body_randomshapesasterrain": 26003,
        "intparam_hierarchychangecounter": 50,
        "jointdynctrl_callback": 16,
        "forcefloatparam_error_y": 5001,
        "msgbox_buttons_yesnocancel": 2,
        "mujoco_dummy_solimplimit5": 46009,
        "mujoco_joint_solreflimit2": 40002,
        "intparam_motionplanning_seed": 35,
        "jointfloatparam_velocity": 2012,
        "objectspecialproperty_detectable": 496,
        "moduleinfo_extversionint": 2,
        "modelproperty_not_renderable": 4,
        "ode_joint_normalcfm": 12005,
        "mujoco_joint_solimpfriction4": 40014,
        "mujoco_dummy_solimplimit4": 46008,
        "drawing_trianglepts": 9,
        "boolparam_rendering_sensor_handling_enabled": 10,
        "syscb_aftercreate": 26,
        "jointfloatparam_kc_c": 2019,
        "shapefloatparam_init_velocity_y": 3001,
        "verbosity_trace": 700,
        "drawing_12percenttransparency": 32768,
        "buttonproperty_closeaction": 4096,
        "vortex_global_constraintlinearkineticloss": 18006,
        "camerafarrayparam_viewfrustum": 9013,
        "buttonproperty_label": 1,
        "boolparam_objproperties_toolbarbutton_enabled": 46,
        "mujoco_joint_armature": 40021,
        "boolparam_fog_enabled": 19,
        "object_path_type": 8,
        "drawing_facingcamera": 131072,
        "physics_mujoco": 4,
        "jointintparam_vortex_dep_handle": 2031,
        "ik_jacobian_transpose_method": 2,
        "physics_ode": 1,
        "modelproperty_not_reset": 128,
        "intparam_edit_mode_type": 14,
        "vortex_joint_p0loss": 21012,
        "syscb_customcallback3": 22,
        "newton_body_restitution": 33003,
        "bullet_constraintsolvertype_nncg": 1,
        "navigation_createpathpoint": 256,
        "mujoco_body_solimp3": 43008,
        "verbosity_default": 400,
        "jointdynctrl_velocity": 4,
        "vortex_joint_p1loss": 21018,
        "mujoco_joint_dependentobjectid": 41002,
        "stringparam_app_arg9": 10,
        "mujoco_global_computeinertias": 39001,
        "intparam_program_full_version": 39,
        "mujoco_dummy_proxyjointid": 47002,
        "pathproperty_flat_path": 64,
        "scriptattribute_scripttype": 7,
        "navigation_camerashift": 1,
        "boolparam_pause_toolbarbutton_enabled": 43,
        "ode_joint_fudgefactor": 12004,
        "stringparam_app_arg6": 7,
        "mujoco_global_cone": 38007,
        "jointintparam_ctrl_enabled": 2001,
        "ik_damped_least_squares_method": 1,
        "intparam_mouse_y": 23,
        "mujoco_body_solref1": 43004,
        "bullet_body_restitution": 6001,
        "drawing_overlay": 262144,
        "handleflag_extended": 4194304,
        "vortex_body_seclinearaxisstaticfrictionscale": 24007,
        "vortex_joint_a0stiffness": 21031,
        "syscb_trigger": 31,
        "bullet_body_bitcoded": 7001,
        "displayattribute_useauxcomponent": 524288,
        "scriptattribute_debuglevel": 6,
        "shapefloatparam_texture_g": 3011,
        "vortex_global_constraintangularkineticloss": 18009,
        "vortex_body_primlinearaxisfriction": 24001,
        "shapeintparam_respondable_mask": 3019,
        "boolparam_use_glfinish_cmd": 26,
        "message_prox_sensor_select_up": 10,
        "stringparam_machine_id": 119,
        "objintparam_parent_role": 30,
        "ode_global_quickstep": 11002,
        "newton_global_multithreading": 29001,
        "mujoco_joint_solimplimit5": 40007,
        "mill_pyramid_subtype": 40,
        "stringparam_pythondir": 137,
        "mujoco_global_balanceinertias": 39004,
        "ode_body_softcfm": 15003,
        "stringparam_addondir": 143,
        "boolparam_fullscreen": 33,
        "floatparam_stereo_distance": 2,
        "handleflag_keeporiginal": 4194304,
        "shapeintparam_static": 3003,
        "childscriptattribute_automaticcascadingcalls": 3,
        "filtercomponent_sharpen": 20,
        "dynmat_wheel": 2310019,
        "objintparam_visible": 36,
        "vortex_body_linearvelocitydamping": 24016,
        "buttonproperty_ignoremouse": 128,
        "primitiveshape_cuboid": 3,
        "shapefloatparam_mass": 3005,
        "bullet_global_constraintsolvertype": 1003,
        "jointfloatparam_error_g": 2027,
        "dummy_linktype_ik_tip_target": 5,
        "mujoco_dummy_bitcoded": 47001,
        "intparam_server_port_next": 15,
        "verbosity_onlyterminal": 65536,
        "drawing_trianglepoints": 3,
        "simulation_advancing": 16,
        "displayattribute_colorcodedtriangles": 134217728,
        "stringparam_scene_path": 14,
        "boolparam_console_visible": 1,
        "vortex_body_secangularaxisslide": 24021,
        "appobj_ui_type": 116,
        "dummyfloatparam_size": 10003,
        "dynmat_nofriction": 2310016,
        "customizationscriptcall_firstaftersimulation": 5,
        "syscb_moduleentry": 33,
        "jointfloatparam_step_size": 2035,
        "dynmat_floor": 2310021,
        "boolparam_show_w_emitters": 53,
        "intparam_server_port_range": 10,
        "newton_body_fastmoving": 35001,
        "syscb_init": 2,
        "filtercomponent_rotate": 15,
        "shapefloatparam_shading_angle": 3025,
        "customizationscriptcall_aftercopy": 14,
        "lightfloatparam_lin_attenuation": 8004,
        "displayattribute_renderpass": 1,
        "objfloatparam_objbbox_max_x": 18,
        "object_proximitysensor_type": 5,
        "customizationscriptcall_simulationpausefirst": 9,
        "stringparam_datadir": 129,
        "handleflag_reljointbaseframe": 4194304,
        "scriptintparam_type": 2,
        "syscb_beforecopy": 13,
        "buttonproperty_staydown": 8,
        "imgcomb_horizontal": 1,
        "stringparam_verbosity": 121,
        "pure_primitive_cone": 6,
        "intparam_speedmodifier": 36,
        "dynmat_foot": 2310018,
        "vortex_body_autoangulardamping": 26009,
        "distcalcmethod_dl_if_nonzero": 5,
        "drawing_spherepts": 7,
        "objectproperty_hierarchyhiddenmodelchild": 32768,
        "intparam_prox_sensor_select_up": 28,
        "boolparam_collision_handling_enabled": 2,
        "stringparam_statusbarverbosity": 122,
        "stringparam_systemdir": 140,
        "filtercomponent_tobuffer2": 6,
        "banner_left": 1,
        "vortex_global_constraintlineardamping": 18005,
        "scriptdebug_vars_interval": 2,
        "vortex_body_normangaxissameasprimangaxis": 26008,
        "rml_keep_current_vel_if_fallback_strategy": 0,
        "boolparam_aux_clip_planes_enabled": 23,
        "visionintparam_windowed_pos_x": 1011,
        "mujoco_global_overridesolimp3": 37015,
        "shapeintparam_respondable": 3004,
        "intparam_settings": 13,
        "boolparam_distance_handling_enabled": 3,
        "mujoco_joint_springdamper2": 40020,
        "objectspecialproperty_pathplanning_ignored": 2048,
        "scripttype_mainscript": 0,
        "banner_bitmapfont": 2048,
        "handleflag_assembly": 4194304,
        "ode_global_cfm": 9003,
        "rml_keep_target_vel": 0,
        "mainscriptcall_regular": 6,
        "syscb_thread": 43,
        "buttonproperty_editbox": 3,
        "objectspecialproperty_detectable_capacitive": 256,
        "jointdynctrl_spring": 12,
        "objfloatparam_objbbox_min_z": 17,
        "customizationscriptcall_beforecopy": 13,
        "stringparam_sandboxlang": 144,
        "mill_disc_subtype": 42,
        "vortex_global_computeinertias": 20005,
        "shapeintparam_component_cnt": 3028,
        "bullet_global_fullinternalscaling": 2001,
        "navigation_camerarotaterightbutton": 8192,
        "vortex_joint_dependentobjectid": 22006,
        "intparam_qt_version": 16,
        "syscb_actuation": 6,
        "filtercomponent_subtractfrombuffer1": 31,
        "vortex_joint_p0frictionloss": 21017,
        "syscb_resume": 10,
        "filtercomponent_todepthoutput": 38,
        "distcalcmethod_dl_and_dac": 3,
        "bullet_body_angulardamping": 6005,
        "filtercomponent_blobextraction": 34,
        "boolparam_scene_closing": 52,
        "displayattribute_mainselection": 32,
        "vortex_body_materialuniqueid": 25008,
        "buffer_base64": 12,
        "arrayparam_fog_color": 2,
        "bullet_body_oldfriction": 6002,
        "vortex_joint_a0damping": 21032,
        "buttonproperty_horizontallycentered": 64,
        "mujoco_joint_solimpfriction1": 40011,
        "simulation_advancing_lastbeforestop": 22,
        "cameraintparam_rendering_attributes": 9003,
        "objintparam_child_role": 29,
        "newton_body_bitcoded": 34001,
        "scriptintparam_handle": 3,
        "message_prox_sensor_select_down": 9,
        "objfloatparam_modelbbox_min_x": 21,
        "stream_transf_cumulative": 3,
        "vortex_body_compliance": 24011,
        "stream_transf_integral": 2,
        "moduleinfo_builddatestr": 1,
        "buttonproperty_transparent": 512,
        "shape_multishape_subtype": 21,
        "intparam_infotext_style": 12,
        "boolparam_hierarchy_visible": 0,
        "scriptattribute_executionorder": 1,
        "boolparam_realtime_simulation": 25,
        "filtercomponent_swapbuffers": 9,
        "vortex_bodyfrictionmodel_none": 6,
        "syscb_aos_resume": 17,
        "displayattribute_forvisionsensor": 2048,
        "mujoco_dummy_damping": 46013,
        "boolparam_execunsafe": 58,
        "syscb_contactcallback": 19,
        "callbackid_rossubscriber": 1,
        "mujoco_joint_polycoef2": 40024,
        "intparam_error_report_mode": 0,
        "forcefloatparam_error_b": 5004,
        "newton_global_stepsize": 27001,
        "msgbox_return_ok": 3,
        "intparam_program_version": 1,
        "navigation_cameratilt": 4,
        "boolparam_proximity_sensor_handling_enabled": 9,
        "visionintparam_pov_focal_blur": 1013,
        "imgcomb_vertical": 0,
        "mujoco_global_overridesolref1": 37011,
        "vortex_joint_motorconstraintfrictioncoeff": 21009,
        "dlgstyle_dont_center": 32,
        "bullet_constraintsolvertype_dantzig": 2,
        "mujoco_global_wind2": 37004,
        "rml_only_time_sync": 1,
        "intparam_idle_fps": 26,
        "intparam_prox_sensor_select_down": 27,
        "intparam_mouse_buttons": 31,
        "buttonproperty_slider": 2,
        "floatparam_mouse_wheel_zoom_factor": 4,
        "physics_vortex": 2,
        "syscb_contact": 41,
        "syscb_beforeinstanceswitch": 11,
        "filtercomponent_colorsegmentation": 33,
        "intparam_objectcreationcounter": 48,
        "sim_lang_lua": 0,
        "addonscriptcall_restarting": 17,
        "boolparam_objectshift_toolbarbutton_enabled": 37,
        "stringparam_app_arg1": 2,
        "scriptstringparam_text": 2,
        "vortex_joint_a1damping": 21038,
        "stringparam_scene_path_and_name": 13,
        "objectproperty_dontshowasinsidemodel": 256,
        "scripttype_threaded": 240,
        "mujoco_body_solimp5": 43010,
        "stringparam_resourcesdir": 141,
        "vortex_joint_p2damping": 21026,
        "objectspecialproperty_measurable": 2,
        "scriptexecorder_first": 0,
        "childscriptcall_cleanup": 1,
        "verbosity_undecorated": 61440,
        "objintparam_manipulation_permissions": 31,
        "vortex_joint_motorconstraintfrictionmaxforce": 21010,
        "mujoco_body_condim": 44001,
        "dummyfloatparam_follow_path_offset": 10002,
        "visionfloatparam_near_clipping": 1000,
        "msgbox_buttons_ok": 0,
        "vortex_global_autosleep": 20001,
        "object_pointcloud_type": 16,
        "script_call_error": 16,
        "vortex_global_constraintangulardamping": 18008,
        "message_model_loaded": 4,
        "displayattribute_ignorerenderableflag": 1048576,
        "buffer_uint8argb": 11,
        "syscb_beforemainscript": 29,
        "displayattribute_nopointclouds": 16777216,
        "mujoco_joint_solreffriction2": 40010,
        "appobj_collision_type": 110,
        "drawing_persistent": 1048576,
        "newton_global_computeinertias": 29004,
        "objectspecialproperty_detectable_infrared": 32,
        "drawing_triangles": 2,
        "vortex_global_constraintlinearcompliance": 18004,
        "bullet_body_friction": 6003,
        "mujoco_joint_solimplimit3": 40005,
        "navigation_camerarotate": 2,
        "filtercomponent_tobuffer1": 5,
        "filtercomponent_resize": 17,
        "banner_clicktriggersevent": 64,
        "texturemap_cylinder": 1,
        "mujoco_joint_polycoef5": 40027,
        "customizationscriptattribute_activeduringsimulation": 0,
        "physics_bullet": 0,
        "simulation_advancing_firstafterstop": 16,
        "boolparam_exit_request": 41,
        "navigation_camerazoomwheel": 4096,
        "dlgret_cancel": 2,
        "newton_body_staticfriction": 33001,
        "navigation_objectshift": 7,
        "jointfloatparam_error_b": 2026,
        "camerafloatparam_far_clipping": 9009,
        "objfloatparam_size_factor": 34,
        "buttonproperty_rollupaction": 2048,
        "particle_invisible": 512,
        "customizationscriptcall_firstafterinstanceswitch": 12,
        "displayattribute_forcewireframe": 64,
        "customizationscriptcall_simulationpauselast": 10,
        "filedlg_type_load_multiple": 2,
        "displayattribute_pickpass": 4,
        "jointfloatparam_intrinsic_qx": 2008,
        "vortex_joint_dependencyfactor": 21048,
        "intparam_verbosity": 40,
        "api_warning_output": 4,
        "vortex_joint_a2frictioncoeff": 21045,
        "drawing_itemcolors": 32,
        "simulation_stopped": 0,
        "filtercomponent_3x3filter": 18,
        "ode_body_friction": 15001,
        "intparam_mouseclickcounterdown": 46,
        "mujoco_global_nconmax": 38006,
        "childscriptcall_sensing": 7,
        "handle_world": -1,
        "objintparam_collection_self_collision_indicator": 27,
        "object_visionsensor_type": 9,
        "bullet_joint_pospid3": 3008,
        "handle_chain": -7,
        "particle_roughspheres": 3,
        "displayattribute_forbidwireframe": 128,
        "message_ui_button_state_change": 0,
        "shapefloatparam_init_velocity_b": 3021,
        "bullet_global_computeinertias": 2002,
        "intparam_core_count": 24,
        "primitiveshape_spheroid": 4,
        "navigation_clickselection": 512,
        "ik_undamped_pseudo_inverse_method": 3,
        "particle_cyclic": 8192,
        "scriptthreadresume_sensing_last": 4,
        "particle_particlerespondable": 128,
        "handleflag_altname": 4194304,
        "ode_global_constraintsolvingiterations": 10001,
        "colorcomponent_emission": 3,
        "customizationscriptcall_simulationsensing": 7,
        "particle_itemdensities": 2048,
        "millintparam_volume_type": 11000,
        "dummylink_dynloopclosure": 0,
        "pathproperty_show_position": 128,
        "rml_disable_extremum_motion_states_calc": 0,
        "forcefloatparam_error_angle": 5007,
        "visionintparam_windowed_size_y": 1010,
        "camerafloatparam_pov_aperture": 9006,
        "modelproperty_not_detectable": 8,
        "object_forcesensor_type": 12,
        "pure_primitive_plane": 1,
        "primitiveshape_cylinder": 5,
        "lightfloatparam_const_attenuation": 8003,
        "vortex_global_multithreading": 20002,
        "handleflag_togglevisibility": 4194304,
        "colorcomponent_ambient": 0,
        "handleflag_silenterror": 33554432,
        "ode_joint_pospid1": 12006,
        "jointmode_passive": 0,
        "filtercomponent_horizontalflip": 13,
        "banner_backfaceculling": 512,
        "handleflag_resetforce": 4194304,
        "ik_y_constraint": 2,
        "vortex_joint_a1stiffness": 21037,
        "forcefloatparam_error_z": 5002,
        "ik_x_constraint": 1,
        "displayattribute_thickEdges": 65536,
        "objfloatparam_modelbbox_min_y": 22,
        "volume_ray": 4,
        "objfloatparam_objbbox_max_y": 19,
        "vortex_bodyfrictionmodel_box": 0,
        "vortex_body_seclinearaxisslide": 24019,
        "mujoco_global_overridesolimp4": 37016,
        "script_main_not_called": 2,
        "particle_water": 32768,
        "vortex_body_primangularaxisstaticfrictionscale": 24008,
        "shapeintparam_edge_borders_hidden": 3027,
        "customizationscriptattribute_cleanupbeforesave": 5,
        "jointfloatparam_ik_weight": 2021,
        "colorcomponent_ambient_diffuse": 0,
        "shapeintparam_kinematic": 3030,
        "drawing_followparentvisibility": 2048,
        "vortex_bodyfrictionmodel_scaledboxfast": 4,
        "filtercomponent_correlationwithbuffer1": 32,
        "message_keypress": 6,
        "vortex_joint_p2loss": 21024,
        "shapeintparam_respondablesuspendcnt": 3031,
        "jointfloatparam_spherical_qz": 2015,
        "syscb_aftercopy": 14,
        "displayattribute_depthpass": 2,
        "syscb_jointcallback": 18,
        "visionintparam_disabled_light_components": 1006,
        "mujoco_joint_pospid2": 40029,
        "shapefloatparam_init_velocity_z": 3002,
        "scriptdebug_allcalls": 3,
        "verbosity_useglobal": -1,
        "vortex_body_damping": 24012,
        "pathproperty_show_line": 1,
        "syscb_cleanup": 1,
        "vortex_global_constraintangularcompliance": 18007,
        "msgbox_return_cancel": 0,
        "pure_primitive_none": 0,
        "ruckig_timesync": 1,
        "jointintparam_dynvelctrltype": 2040,
        "stringparam_app_arg4": 5,
        "lightfloatparam_spot_cutoff": 8002,
        "scriptintparam_execcount": 1,
        "ode_global_fullinternalscaling": 11001,
        "jointfloatparam_pid_i": 2003,
        "vortex_body_restitutionthreshold": 24014,
        "objectproperty_depthinvisible": 4096,
        "verbosity_scriptwarnings": 430,
        "stringparam_importexportdir": 130,
        "mujoco_dummy_solreflimit1": 46003,
        "filtercomponent_rectangularcut": 22,
        "jointfloatparam_vortex_dep_offset": 2033,
        "bullet_body_usenondefaultcollisionmarginconvex": 8003,
        "ruckig_phasesync": 0,
        "shapefloatparam_texture_scaling_y": 3013,
        "vortex_body_primlinearaxisstaticfrictionscale": 24006,
        "stringparam_mujocodir": 138,
        "objectspecialproperty_detectable_laser": 64,
        "intparam_mouseclickcounterup": 47,
        "buffer_int32": 5,
        "verbosity_infos": 500,
        "vortex_body_convexshapesasrandom": 26002,
        "scripttype_customizationscript": 6,
        "objstringparam_dna": 33,
        "drawing_25percenttransparency": 16384,
        "script_lua_error": 8,
        "mujoco_body_solref2": 43005,
        "msgbox_return_error": 4,
        "boolparam_play_toolbarbutton_enabled": 42,
        "ode_body_maxcontacts": 16001,
        "arrayparam_fog": 1,
        "displayattribute_dynamiccontentonly": 131072,
        "light_spot_subtype": 2,
        "mujoco_joint_solimpfriction2": 40012,
        "boolparam_calcmodules_toolbarbutton_enabled": 47,
        "mujoco_global_nstack": 38009,
        "dlgret_ok": 1,
        "dynmat_lowfriction": 2310015,
        "stringparam_app_arg3": 4,
        "jointfloatparam_intrinsic_qw": 2011,
        "jointfloatparam_spherical_qw": 2016,
        "navigation_shiftselection": 2048,
        "buffer_split": 13,
        "syscb_beforedelete": 24,
        "visionintparam_render_mode": 1017,
        "mill_cone_subtype": 43,
        "jointintparam_velocity_lock": 2030,
        "visionintparam_rendering_attributes": 1007,
        "visionintparam_windowed_size_x": 1009,
        "buffer_uint8": 0,
        "stringparam_app_arg5": 6,
        "object_mirror_type": 14,
        "shape_simpleshape_subtype": 20,
        "stringparam_tempdir": 127,
        "jointfloatparam_error_angle": 2029,
        "proximitysensor_ray_subtype": 34,
        "jointfloatparam_spherical_qx": 2013,
        "handle_parent": -11,
        "verbosity_questions": 410,
        "distcalcmethod_max_dl_dac": 2,
        "intparam_exitcode": 44,
        "scripttype_addonscript": 2,
        "pure_primitive_cylinder": 5,
        "boolparam_force_calcstruct_all": 40,
        "vortex_joint_upperlimitstiffness": 21004,
        "scriptstringparam_description": 0,
        "jointfloatparam_error_pos": 2028,
        "vortex_joint_lowerlimitstiffness": 21003,
        "syscb_dyn": 40,
        "objintparam_visibility_layer": 10,
        "texturemap_plane": 0,
        "ik_alpha_beta_constraint": 8,
        "appobj_object_type": 109,
        "shapefloatparam_texture_scaling_x": 3012,
        "vortex_joint_a0frictionloss": 21035,
        "scriptattribute_executioncount": 2,
        "newton_joint_pospid3": 30005,
        "scriptthreadresume_actuation_first": 1,
        "scriptattribute_scripthandle": 8,
        "proxintparam_ray_invisibility": 4000,
        "particle_spheres": 4,
        "vortex_body_seclinearaxisfrictionmodel": 25002,
        "navigation_objectrotate": 8,
        "filedlg_type_load": 0,
        "jointfloatparam_maxaccel": 2037,
        "modelproperty_not_dynamic": 32,
        "primitiveshape_none": 0,
        "syscb_aos_run": 15,
        "drawing_quadpoints": 4,
        "message_bannerclicked": 7,
        "bullet_global_stepsize": 1,
        "texturemap_sphere": 2,
        "boolparam_rml4_available": 21,
        "ruckig_minaccel": 512,
        "visionintparam_windowed_pos_y": 1012,
        "script_reentrance_error": 4,
        "filtercomponent_keeporremovecolors": 26,
        "handle_inverse": -14,
        "mujoco_body_solimp4": 43009,
        "volume_randomizedray": 5,
        "vortex_body_fastmoving": 26004,
        "buttonproperty_verticallycentered": 8192,
        "mujoco_joint_frictionloss": 40008,
        "boolparam_browser_visible": 12,
        "scriptintparam_execorder": 0,
        "objfloatparam_objbbox_min_y": 16,
        "objintparam_hierarchycolor": 38,
        "appobj_script_type": 117,
        "appobj_2delement_type": 116,
        "intparam_objectdestructioncounter": 49,
        "stringparam_tempscenedir": 128,
        "simulation_advancing_lastbeforepause": 19,
        "forcefloatparam_error_x": 5000,
        "vortex_joint_p1frictionmaxforce": 21022,
        "vortex_joint_bitcoded": 22001,
        "vortex_body_autosleepangularaccelthreshold": 24031,
        "scriptdebug_callsandvars": 5,
        "object_octree_type": 15,
        "mujoco_joint_margin": 40022,
        "msgbox_buttons_okcancel": 3,
        "mujoco_joint_stiffness": 40016,
        "vortex_joint_a2frictionmaxforce": 21046,
        "objfloatparam_abs_x_velocity": 11,
        "proxintparam_entity_to_detect": 4002,
        "script_main_script_nonexistent": 1,
        "stringparam_logfilter": 124,
        "vortex_joint_upperlimitrestitution": 21006,
        "objectproperty_ignoreviewfitting": 1,
        "dlgret_yes": 3,
        "intparam_work_thread_calc_time_ms": 25,
        "plugininfo_verbosity": 3,
        "jointfloatparam_error_z": 2024,
        "scripttype_addonfunction": 3,
        "camerafloatparam_ortho_size": 9002,
        "cameraintparam_pov_focal_blur": 9004,
        "lightintparam_pov_casts_shadows": 8000,
        "mujoco_dummy_solimplimit2": 46006,
        "dynmat_gripper": 2310020,
        "handleflag_greyscale": 4194304,
        "cameraintparam_pov_blur_samples": 9007,
        "banner_facingcamera": 128,
        "scriptdebug_none": 0,
        "vortex_global_stepsize": 18001,
        "syscb_sensing": 7,
        "msgbox_type_info": 0,
        "mirrorfloatparam_reflectance": 12002,
        "buttonproperty_downupevent": 16384,
        "mirrorintparam_enable": 12003,
        "bullet_global_internalscalingfactor": 2,
        "stringparam_scene_name": 15,
        "jointfloatparam_maxvel": 2036,
        "drawing_quadpts": 10,
        "filtercomponent_pixelchange": 36,
        "bullet_global_collisionmarginfactor": 3,
        "graphintparam_needs_refresh": 10500,
        "mujoco_dummy_solimplimit3": 46007,
        "buttonproperty_enabled": 16,
        "volume_cylinder": 1,
        "pathproperty_show_orientation": 2,
        "addonscriptcall_run": 15,
        "boolparam_infotext_visible": 17,
        "newton_joint_objectid": 31001,
        "mujoco_global_overridemargin": 37010,
        "displayattribute_mirror": 262144,
        "bullet_joint_normalcfm": 3003,
        "bullet_joint_pospid2": 3007,
        "bullet_body_lineardamping": 6004,
        "object_light_type": 13,
        "object_mill_type": 11,
        "objstringparam_unique_id": 35,
        "vortex_body_primaxisvectory": 24035,
        "bullet_body_sticky": 8001,
        "boolparam_force_show_wireless_emission": 27,
        "buttonproperty_borderless": 32,
        "displayattribute_noopenglcallbacks": 2097152,
        "bullet_body_usenondefaultcollisionmargin": 8002,
        "ruckig_minvel": 256,
        "vortex_body_secangaxissameasprimangaxis": 26007,
        "intparam_work_thread_count": 21,
        "vortex_body_pureshapesasconvex": 26001,
        "vortex_joint_upperlimitmaxforce": 21008,
        "newton_joint_dependentobjectid": 31002,
        "dummy_linktype_dynamics_force_constraint": 1,
        "newton_joint_pospid1": 30003,
        "vortex_body_autosleeplinearaccelthreshold": 24029,
        "object_renderingsensor_type": 9,
        "moduleinfo_extversionstr": 0,
        "mujoco_joint_polycoef4": 40026,
        "vortex_joint_objectid": 22005,
        "drawing_cubepoints": 6,
        "vortex_joint_p2frictionmaxforce": 21028,
        "vortex_joint_a1loss": 21036,
        "msgbox_type_warning": 2,
        "navigation_passive": 0,
        "intparam_dynamic_warning_disabled_mask": 32,
        "ode_body_lineardamping": 15004,
        "syscb_regular": 6,
        "arrayparam_background_color1": 3,
        "syscb_userconfig": 32,
        "proxintparam_volume_type": 4001,
        "vortex_joint_proportionalmotorfriction": 23002,
        "script_no_error": 0,
        "filtercomponent_shift": 16,
        "texturemap_cube": 3,
        "mujoco_dummy_solreflimit2": 46004,
        "jointmode_ikdependent": 3,
        "customizationscriptcall_lastbeforesimulation": 4,
        "visionintparam_resolution_y": 1003,
        "vortex_joint_p2frictionloss": 21029,
        "lightfloatparam_spot_exponent": 8001,
        "vortex_body_restitution": 24013,
        "vortex_joint_upperlimitdamping": 21002,
        "mujoco_joint_solreflimit1": 40001,
        "syscb_suspend": 9,
        "vortex_joint_pospid2": 21053,
        "scriptexecorder_normal": 1,
        "syscb_beforesimulation": 4,
        "vortex_joint_p0frictionmaxforce": 21016,
        "rml_only_phase_sync": 1,
        "syscb_dyncallback": 28,
        "jointfloatparam_error_y": 2023,
        "vortex_joint_p1damping": 21020,
        "rml_no_sync": 3,
        "filedlg_type_folder": 3,
        "jointmode_force": 5,
        "simulation_paused": 8,
        "dummy_linktype_dynamics_loop_closure": 0,
        "newton_global_bitcoded": 28002,
        "vortex_joint_a0loss": 21030,
        "vortex_joint_a0frictionmaxforce": 21034,
        "newton_body_angulardrag": 33005,
        "scriptthreadresume_allnotyetresumed": -1,
        "vortex_body_primaxisvectorz": 24036,
        "ode_body_softerp": 15002,
        "handle_scene": -12,
        "handleflag_depthbuffer": 8388608,
        "object_dummy_type": 4,
        "vortex_body_primlinearaxisfrictionmodel": 25001,
        "bullet_joint_stopcfm": 3002,
        "intparam_statusbarverbosity": 41,
        "mujoco_body_friction2": 43002,
        "filtercomponent_normalize": 24,
        "syscb_customcallback2": 21,
        "camerafloatparam_near_clipping": 9008,
        "handleflag_axis": 4194304,
        "filtercomponent_originaldepth": 2,
        "vortex_body_secangularaxisfriction": 24004,
        "syscb_afterdelete": 25,
        "vortex_joint_p1frictioncoeff": 21021,
        "bullet_body_nondefaultcollisionmargingfactorconvex": 6007,
        "handleflag_camera": 4194304,
        "vortex_joint_p0stiffness": 21013,
        "drawing_spherepoints": 7,
        "vortex_body_secangularaxisslip": 24026,
        "scriptexecorder_last": 2,
        "objfloatparam_modelbbox_min_z": 23,
        "jointfloatparam_pid_d": 2004,
        "mujoco_global_viscosity": 37007,
        "vortex_body_secmangulararaxisfrictionmodel": 25004,
        "shapefloatparam_init_ang_velocity_x": 3020,
        "vortex_body_autosleepsteplivethreshold": 25007,
        "syscb_aftersimulation": 5,
        "intparam_dynamic_engine": 8,
        "jointfloatparam_screwlead": 2042,
        "stringparam_app_arg7": 8,
        "customizationscriptcall_initialization": 2,
        "handleflag_codedstring": 4194304,
        "visionfloatparam_far_clipping": 1001,
        "mujoco_global_overridesolimp2": 37014,
        "msgbox_buttons_yesno": 1,
        "mujoco_global_solver": 38004,
        "mujoco_global_multithreaded": 39002,
        "mujoco_joint_springref": 40018,
        "handleflag_wxyzquat": 16777216,
        "appobj_pathplanning_type": 118,
        "objfloatparam_modelbbox_max_y": 25,
        "vortex_body_secangularaxisstaticfrictionscale": 24009,
        "dummyintparam_link_type": 10000,
        "filtercomponent_5x5filter": 19,
        "filtercomponent_multiplywithbuffer1": 12,
        "buffer_int8": 1,
        "scriptdebug_vars": 4,
        "buffer_uint8bgr": 9,
        "syscb_customcallback4": 23,
        "handle_all": -2,
        "mujoco_global_overridesolimp1": 37013,
        "light_omnidirectional_subtype": 1,
        "callbackid_dynstep": 2,
        "physics_newton": 3,
        "objectproperty_selectable": 32,
        "filtercomponent_uniformimage": 3,
        "objectspecialproperty_detectable_ultrasonic": 16,
        "filtercomponent_tooutput": 4,
        "newton_body_lineardrag": 33004,
        "handleflag_rawvalue": 16777216,
        "floatparam_rand": 0,
        "particle_points4": 2,
        "mujoco_global_overridesolref2": 37012,
        "distcalcmethod_dl": 0,
        "filtercomponent_customized": 1000,
        "boolparam_scene_and_model_load_messages": 13,
        "shapefloatparam_texture_x": 3006,
        "filtercomponent_circularcut": 23,
        "verbosity_scripterrors": 420,
        "buffer_int16": 3,
        "mujoco_joint_springdamper1": 40019,
        "bullet_global_bitcoded": 1002,
        "vortex_body_autoslip": 26005,
        "mujoco_dummy_stiffness": 46012,
        "particle_itemsizes": 1024,
        "lightfloatparam_quad_attenuation": 8005,
        "visionfloatparam_pov_blur_distance": 1014,
        "msgbox_return_yes": 2,
        "mujoco_dummy_springlength": 46011,
        "banner_keepsamesize": 1024,
        "pure_primitive_heightfield": 7,
        "mujoco_joint_pospid3": 40030,
        "joint_prismatic_subtype": 11,
        "childscriptcall_actuation": 6,
        "arrayparam_gravity": 0,
        "drawing_local": 8388608,
        "intparam_program_revision": 30
    },
    "sim_plugin_namespaces": {
        "simZMQ": {
            "EMFILE": 24,
            "CURVE_PUBLICKEY": 48,
            "ENODEV": 19,
            "PROTOCOL_ERROR_ZAP_BAD_VERSION": 536870915,
            "SRCFD": 2,
            "ENOENT": 2,
            "EVENT_MONITOR_STOPPED": 1024,
            "RCVMORE": 13,
            "VMCI_BUFFER_MAX_SIZE": 87,
            "EVENT_CONNECTED": 1,
            "IO_THREADS": 1,
            "XREQ": 5,
            "PROTOCOL_ERROR_ZAP_INVALID_STATUS_CODE": 536870916,
            "MAX_MSGSZ": 5,
            "CURVE_SERVERKEY": 50,
            "MULTICAST_HOPS": 25,
            "EHOSTUNREACH": 113,
            "EFSM": 156384763,
            "PUB": 1,
            "MORE": 1,
            "EINTR": 4,
            "IMMEDIATE": 39,
            "EPROTONOSUPPORT": 93,
            "GSSAPI": 3,
            "SUB": 2,
            "STREAM_NOTIFY": 73,
            "CONFLATE": 54,
            "ROUTER_RAW": 41,
            "CURVE": 2,
            "THREAD_SCHED_POLICY_DFLT": -1,
            "ROUTER_MANDATORY": 33,
            "IPC_FILTER_GID": 60,
            "PROTOCOL_ERROR_ZMTP_INVALID_METADATA": 268435480,
            "TCP_KEEPALIVE_IDLE": 36,
            "GSSAPI_PRINCIPAL_NAMETYPE": 90,
            "PROTOCOL_ERROR_ZMTP_MALFORMED_COMMAND_HELLO": 268435475,
            "DEALER": 5,
            "SOCKET_LIMIT": 3,
            "EVENT_CONNECT_DELAYED": 2,
            "PUSH": 8,
            "GSSAPI_NT_KRB5_PRINCIPAL": 2,
            "EVENT_DISCONNECTED": 512,
            "RECONNECT_IVL": 18,
            "GSSAPI_PLAINTEXT": 65,
            "TOS": 57,
            "CURVE_SECRETKEY": 49,
            "SHARED": 3,
            "RECOVERY_IVL": 9,
            "THREAD_AFFINITY_CPU_REMOVE": 8,
            "ENOTSOCK": 88,
            "POLLIN": 1,
            "BLOCKY": 70,
            "POLLPRI": 8,
            "XSUB": 10,
            "IPC_FILTER_PID": 58,
            "PROTOCOL_ERROR_ZAP_UNSPECIFIED": 536870912,
            "PLAIN_USERNAME": 45,
            "ROUTER_HANDOVER": 56,
            "XPUB_VERBOSER": 78,
            "PROBE_ROUTER": 51,
            "INVERT_MATCHING": 74,
            "IPC_FILTER_UID": 59,
            "GSSAPI_SERVICE_PRINCIPAL_NAMETYPE": 91,
            "PLAIN_PASSWORD": 46,
            "RECONNECT_IVL_MAX": 21,
            "SUBSCRIBE": 6,
            "DELAY_ATTACH_ON_CONNECT": 39,
            "HAUSNUMERO": 156384712,
            "GROUP_MAX_LENGTH": 255,
            "POLLITEMS_DFLT": 16,
            "PAIR": 0,
            "SOCKS_PROXY": 68,
            "EVENT_BIND_FAILED": 16,
            "IPV6": 42,
            "PROTOCOL_ERROR_ZMTP_MECHANISM_MISMATCH": 285212674,
            "EADDRNOTAVAIL": 99,
            "EINVAL": 22,
            "CONNECT_RID": 61,
            "LAST_ENDPOINT": 32,
            "SNDHWM": 23,
            "STREAMER": 1,
            "MSG_T_SIZE": 6,
            "REP": 4,
            "QUEUE": 3,
            "PROTOCOL_ERROR_ZMTP_MALFORMED_COMMAND_MESSAGE": 268435474,
            "XREP": 6,
            "HAS_CAPABILITIES": 1,
            "NOBLOCK": 1,
            "TCP_ACCEPT_FILTER": 38,
            "EMTHREAD": 156384766,
            "EVENT_ALL": 65535,
            "REQ_CORRELATE": 52,
            "EVENT_LISTENING": 8,
            "XPUB": 9,
            "CONNECT_ROUTING_ID": 61,
            "EVENT_CLOSE_FAILED": 256,
            "RCVTIMEO": 27,
            "PROTOCOL_ERROR_WS_UNSPECIFIED": 805306368,
            "PROTOCOL_ERROR_ZAP_BAD_REQUEST_ID": 536870914,
            "PROTOCOL_ERROR_ZMTP_MALFORMED_COMMAND_WELCOME": 268435479,
            "IO_THREADS_DFLT": 1,
            "PROTOCOL_ERROR_ZMTP_CRYPTOGRAPHIC": 285212673,
            "MAXMSGSIZE": 22,
            "FAIL_UNROUTABLE": 33,
            "GSSAPI_NT_USER_NAME": 1,
            "PROTOCOL_ERROR_ZMTP_UNEXPECTED_COMMAND": 268435457,
            "CONNECT_TIMEOUT": 79,
            "EVENT_ACCEPTED": 32,
            "VMCI_BUFFER_MIN_SIZE": 86,
            "EVENT_CLOSED": 128,
            "TCP_KEEPALIVE_CNT": 35,
            "ROUTING_ID": 5,
            "XPUB_VERBOSE": 40,
            "POLLOUT": 2,
            "EAGAIN": 11,
            "PROTOCOL_ERROR_ZMTP_MALFORMED_COMMAND_READY": 268435478,
            "ENOMEM": 12,
            "RCVBUF": 12,
            "THREAD_PRIORITY_DFLT": -1,
            "PULL": 7,
            "PROTOCOL_ERROR_ZAP_INVALID_METADATA": 536870917,
            "NULL": 0,
            "SNDMORE": 2,
            "REQ": 3,
            "RCVHWM": 24,
            "ETERM": 156384765,
            "ROUTER_BEHAVIOR": 33,
            "PROTOCOL_ERROR_ZMTP_INVALID_SEQUENCE": 268435458,
            "AFFINITY": 4,
            "BINDTODEVICE": 92,
            "LINGER": 17,
            "ENOCOMPATPROTO": 156384764,
            "EVENT_HANDSHAKE_FAILED_NO_DETAIL": 2048,
            "TCP_KEEPALIVE": 34,
            "FD": 14,
            "SNDTIMEO": 28,
            "HEARTBEAT_IVL": 75,
            "IPV4ONLY": 31,
            "PROTOCOL_ERROR_ZAP_MALFORMED_REPLY": 536870913,
            "THREAD_SAFE": 81,
            "VMCI_CONNECT_TIMEOUT": 88,
            "THREAD_AFFINITY_CPU_ADD": 7,
            "THREAD_NAME_PREFIX": 9,
            "HANDSHAKE_IVL": 66,
            "XPUB_WELCOME_MSG": 72,
            "PLAIN_SERVER": 44,
            "THREAD_PRIORITY": 3,
            "GSSAPI_SERVER": 62,
            "PROTOCOL_ERROR_ZMTP_MALFORMED_COMMAND_ERROR": 268435477,
            "PROTOCOL_ERROR_ZMTP_KEY_EXCHANGE": 268435459,
            "MAX_SOCKETS_DFLT": 1023,
            "GSSAPI_PRINCIPAL": 63,
            "EVENT_HANDSHAKE_FAILED_PROTOCOL": 8192,
            "FORWARDER": 2,
            "TYPE": 16,
            "THREAD_SCHED_POLICY": 4,
            "HEARTBEAT_TIMEOUT": 77,
            "MAX_SOCKETS": 2,
            "HEARTBEAT_TTL": 76,
            "ZAP_DOMAIN": 55,
            "VMCI_BUFFER_SIZE": 85,
            "EVENTS": 15,
            "XPUB_NODROP": 69,
            "USE_FD": 89,
            "RATE": 8,
            "MECHANISM": 43,
            "EFAULT": 14,
            "pluginHandle": 3,
            "STREAM": 11,
            "DONTWAIT": 1,
            "EVENT_ACCEPT_FAILED": 64,
            "PROTOCOL_ERROR_ZMTP_MALFORMED_COMMAND_UNSPECIFIED": 268435473,
            "UNSUBSCRIBE": 7,
            "ROUTER": 6,
            "GSSAPI_NT_HOSTBASED": 0,
            "IDENTITY": 5,
            "EVENT_HANDSHAKE_SUCCEEDED": 4096,
            "PLAIN": 1,
            "GSSAPI_SERVICE_PRINCIPAL": 64,
            "MULTICAST_MAXTPDU": 84,
            "TCP_MAXRT": 80,
            "REQ_RELAXED": 53,
            "XPUB_MANUAL": 71,
            "EVENT_CONNECT_RETRIED": 4,
            "TCP_KEEPALIVE_INTVL": 37,
            "ENOTSUP": 95,
            "BACKLOG": 19,
            "SNDBUF": 11,
            "EVENT_HANDSHAKE_FAILED_AUTH": 16384,
            "PROTOCOL_ERROR_ZMTP_UNSPECIFIED": 268435456,
            "EADDRINUSE": 98,
            "POLLERR": 4,
            "CURVE_SERVER": 47,
            "PROTOCOL_ERROR_ZMTP_MALFORMED_COMMAND_INITIATE": 268435476
        }
    },
    "simZMQ": {
        "EMFILE": 24,
        "CURVE_PUBLICKEY": 48,
        "ENODEV": 19,
        "PROTOCOL_ERROR_ZAP_BAD_VERSION": 536870915,
        "SRCFD": 2,
        "ENOENT": 2,
        "EVENT_MONITOR_STOPPED": 1024,
        "RCVMORE": 13,
        "VMCI_BUFFER_MAX_SIZE": 87,
        "EVENT_CONNECTED": 1,
        "IO_THREADS": 1,
        "XREQ": 5,
        "PROTOCOL_ERROR_ZAP_INVALID_STATUS_CODE": 536870916,
        "MAX_MSGSZ": 5,
        "CURVE_SERVERKEY": 50,
        "MULTICAST_HOPS": 25,
        "EHOSTUNREACH": 113,
        "EFSM": 156384763,
        "PUB": 1,
        "MORE": 1,
        "EINTR": 4,
        "IMMEDIATE": 39,
        "EPROTONOSUPPORT": 93,
        "GSSAPI": 3,
        "SUB": 2,
        "STREAM_NOTIFY": 73,
        "CONFLATE": 54,
        "ROUTER_RAW": 41,
        "CURVE": 2,
        "THREAD_SCHED_POLICY_DFLT": -1,
        "ROUTER_MANDATORY": 33,
        "IPC_FILTER_GID": 60,
        "PROTOCOL_ERROR_ZMTP_INVALID_METADATA": 268435480,
        "TCP_KEEPALIVE_IDLE": 36,
        "GSSAPI_PRINCIPAL_NAMETYPE": 90,
        "PROTOCOL_ERROR_ZMTP_MALFORMED_COMMAND_HELLO": 268435475,
        "DEALER": 5,
        "SOCKET_LIMIT": 3,
        "EVENT_CONNECT_DELAYED": 2,
        "PUSH": 8,
        "GSSAPI_NT_KRB5_PRINCIPAL": 2,
        "EVENT_DISCONNECTED": 512,
        "RECONNECT_IVL": 18,
        "GSSAPI_PLAINTEXT": 65,
        "TOS": 57,
        "CURVE_SECRETKEY": 49,
        "SHARED": 3,
        "RECOVERY_IVL": 9,
        "THREAD_AFFINITY_CPU_REMOVE": 8,
        "ENOTSOCK": 88,
        "POLLIN": 1,
        "BLOCKY": 70,
        "POLLPRI": 8,
        "XSUB": 10,
        "IPC_FILTER_PID": 58,
        "PROTOCOL_ERROR_ZAP_UNSPECIFIED": 536870912,
        "PLAIN_USERNAME": 45,
        "ROUTER_HANDOVER": 56,
        "XPUB_VERBOSER": 78,
        "PROBE_ROUTER": 51,
        "INVERT_MATCHING": 74,
        "IPC_FILTER_UID": 59,
        "GSSAPI_SERVICE_PRINCIPAL_NAMETYPE": 91,
        "PLAIN_PASSWORD": 46,
        "RECONNECT_IVL_MAX": 21,
        "SUBSCRIBE": 6,
        "DELAY_ATTACH_ON_CONNECT": 39,
        "HAUSNUMERO": 156384712,
        "GROUP_MAX_LENGTH": 255,
        "POLLITEMS_DFLT": 16,
        "PAIR": 0,
        "SOCKS_PROXY": 68,
        "EVENT_BIND_FAILED": 16,
        "IPV6": 42,
        "PROTOCOL_ERROR_ZMTP_MECHANISM_MISMATCH": 285212674,
        "EADDRNOTAVAIL": 99,
        "EINVAL": 22,
        "CONNECT_RID": 61,
        "LAST_ENDPOINT": 32,
        "SNDHWM": 23,
        "STREAMER": 1,
        "MSG_T_SIZE": 6,
        "REP": 4,
        "QUEUE": 3,
        "PROTOCOL_ERROR_ZMTP_MALFORMED_COMMAND_MESSAGE": 268435474,
        "XREP": 6,
        "HAS_CAPABILITIES": 1,
        "NOBLOCK": 1,
        "TCP_ACCEPT_FILTER": 38,
        "EMTHREAD": 156384766,
        "EVENT_ALL": 65535,
        "REQ_CORRELATE": 52,
        "EVENT_LISTENING": 8,
        "XPUB": 9,
        "CONNECT_ROUTING_ID": 61,
        "EVENT_CLOSE_FAILED": 256,
        "RCVTIMEO": 27,
        "PROTOCOL_ERROR_WS_UNSPECIFIED": 805306368,
        "PROTOCOL_ERROR_ZAP_BAD_REQUEST_ID": 536870914,
        "PROTOCOL_ERROR_ZMTP_MALFORMED_COMMAND_WELCOME": 268435479,
        "IO_THREADS_DFLT": 1,
        "PROTOCOL_ERROR_ZMTP_CRYPTOGRAPHIC": 285212673,
        "MAXMSGSIZE": 22,
        "FAIL_UNROUTABLE": 33,
        "GSSAPI_NT_USER_NAME": 1,
        "PROTOCOL_ERROR_ZMTP_UNEXPECTED_COMMAND": 268435457,
        "CONNECT_TIMEOUT": 79,
        "EVENT_ACCEPTED": 32,
        "VMCI_BUFFER_MIN_SIZE": 86,
        "EVENT_CLOSED": 128,
        "TCP_KEEPALIVE_CNT": 35,
        "ROUTING_ID": 5,
        "XPUB_VERBOSE": 40,
        "POLLOUT": 2,
        "EAGAIN": 11,
        "PROTOCOL_ERROR_ZMTP_MALFORMED_COMMAND_READY": 268435478,
        "ENOMEM": 12,
        "RCVBUF": 12,
        "THREAD_PRIORITY_DFLT": -1,
        "PULL": 7,
        "PROTOCOL_ERROR_ZAP_INVALID_METADATA": 536870917,
        "NULL": 0,
        "SNDMORE": 2,
        "REQ": 3,
        "RCVHWM": 24,
        "ETERM": 156384765,
        "ROUTER_BEHAVIOR": 33,
        "PROTOCOL_ERROR_ZMTP_INVALID_SEQUENCE": 268435458,
        "AFFINITY": 4,
        "BINDTODEVICE": 92,
        "LINGER": 17,
        "ENOCOMPATPROTO": 156384764,
        "EVENT_HANDSHAKE_FAILED_NO_DETAIL": 2048,
        "TCP_KEEPALIVE": 34,
        "FD": 14,
        "SNDTIMEO": 28,
        "HEARTBEAT_IVL": 75,
        "IPV4ONLY": 31,
        "PROTOCOL_ERROR_ZAP_MALFORMED_REPLY": 536870913,
        "THREAD_SAFE": 81,
        "VMCI_CONNECT_TIMEOUT": 88,
        "THREAD_AFFINITY_CPU_ADD": 7,
        "THREAD_NAME_PREFIX": 9,
        "HANDSHAKE_IVL": 66,
        "XPUB_WELCOME_MSG": 72,
        "PLAIN_SERVER": 44,
        "THREAD_PRIORITY": 3,
        "GSSAPI_SERVER": 62,
        "PROTOCOL_ERROR_ZMTP_MALFORMED_COMMAND_ERROR": 268435477,
        "PROTOCOL_ERROR_ZMTP_KEY_EXCHANGE": 268435459,
        "MAX_SOCKETS_DFLT": 1023,
        "GSSAPI_PRINCIPAL": 63,
        "EVENT_HANDSHAKE_FAILED_PROTOCOL": 8192,
        "FORWARDER": 2,
        "TYPE": 16,
        "THREAD_SCHED_POLICY": 4,
        "HEARTBEAT_TIMEOUT": 77,
        "MAX_SOCKETS": 2,
        "HEARTBEAT_TTL": 76,
        "ZAP_DOMAIN": 55,
        "VMCI_BUFFER_SIZE": 85,
        "EVENTS": 15,
        "XPUB_NODROP": 69,
        "USE_FD": 89,
        "RATE": 8,
        "MECHANISM": 43,
        "EFAULT": 14,
        "pluginHandle": 3,
        "STREAM": 11,
        "DONTWAIT": 1,
        "EVENT_ACCEPT_FAILED": 64,
        "PROTOCOL_ERROR_ZMTP_MALFORMED_COMMAND_UNSPECIFIED": 268435473,
        "UNSUBSCRIBE": 7,
        "ROUTER": 6,
        "GSSAPI_NT_HOSTBASED": 0,
        "IDENTITY": 5,
        "EVENT_HANDSHAKE_SUCCEEDED": 4096,
        "PLAIN": 1,
        "GSSAPI_SERVICE_PRINCIPAL": 64,
        "MULTICAST_MAXTPDU": 84,
        "TCP_MAXRT": 80,
        "REQ_RELAXED": 53,
        "XPUB_MANUAL": 71,
        "EVENT_CONNECT_RETRIED": 4,
        "TCP_KEEPALIVE_INTVL": 37,
        "ENOTSUP": 95,
        "BACKLOG": 19,
        "SNDBUF": 11,
        "EVENT_HANDSHAKE_FAILED_AUTH": 16384,
        "PROTOCOL_ERROR_ZMTP_UNSPECIFIED": 268435456,
        "EADDRINUSE": 98,
        "POLLERR": 4,
        "CURVE_SERVER": 47,
        "PROTOCOL_ERROR_ZMTP_MALFORMED_COMMAND_INITIATE": 268435476
    }
}